{"data_mtime":1764903502,"dep_lines":[1,2,16,1,1,1,1],"dep_prios":[5,5,5,5,30,30,30],"dependencies":["types","typing","attrs","builtins","abc","contextlib","re"],"hash":"7ed996de6e0a277a507085c08fe05e8d3ec163865faab0b51bee56ed7be83ddb","id":"attr.validators","ignore_all":true,"interface_hash":"40a665b3dc7f090d65fdf1e17b519dd88f0c2a995057e670dc69716a4c06d9d9","mtime":1764895044,"options":{"allow_redefinition":false,"allow_untyped_globals":false,"always_false":[],"always_true":[],"bazel":false,"check_untyped_defs":true,"disable_bytearray_promotion":false,"disable_error_code":[],"disable_memoryview_promotion":false,"disabled_error_codes":[],"disallow_any_decorated":false,"disallow_any_explicit":false,"disallow_any_expr":false,"disallow_any_generics":true,"disallow_any_unimported":false,"disallow_incomplete_defs":true,"disallow_subclassing_any":true,"disallow_untyped_calls":true,"disallow_untyped_decorators":true,"disallow_untyped_defs":true,"enable_error_code":[],"enabled_error_codes":[],"extra_checks":true,"follow_imports":"normal","follow_imports_for_stubs":false,"ignore_errors":false,"ignore_missing_imports":false,"implicit_optional":false,"implicit_reexport":false,"local_partial_types":false,"mypyc":false,"old_type_inference":false,"platform":"win32","plugins":[],"strict_concatenate":false,"strict_equality":true,"strict_optional":true,"warn_no_return":true,"warn_return_any":true,"warn_unreachable":true,"warn_unused_ignores":true},"path":"C:\\Users\\sgtsl\\PROJECTS\\ARC_Saga\\.venv\\Lib\\site-packages\\attr\\validators.pyi","plugin_data":null,"size":4082,"suppressed":[],"version_id":"1.7.0"}