{"data_mtime":1764894867,"dep_lines":[4,3,1,1,1,1,1],"dep_prios":[5,5,5,5,30,30,30],"dependencies":["anyio._core._tasks","anyio.abc","__future__","builtins","abc","anyio.abc._resources","typing"],"hash":"35b994e4ee545f7c44c800a7926617dbc166c1d97e7fe9f2d2d1f29b6e9ed30d","id":"anyio._core._resources","ignore_all":true,"interface_hash":"3b241a0cc4d232b0438106f56d4204796199005eb90f59233bae98bf803ee7f8","mtime":1764831123,"options":{"allow_redefinition":false,"allow_untyped_globals":false,"always_false":[],"always_true":[],"bazel":false,"check_untyped_defs":true,"disable_bytearray_promotion":false,"disable_error_code":[],"disable_memoryview_promotion":false,"disabled_error_codes":[],"disallow_any_decorated":false,"disallow_any_explicit":false,"disallow_any_expr":false,"disallow_any_generics":true,"disallow_any_unimported":false,"disallow_incomplete_defs":true,"disallow_subclassing_any":true,"disallow_untyped_calls":true,"disallow_untyped_decorators":true,"disallow_untyped_defs":true,"enable_error_code":[],"enabled_error_codes":[],"extra_checks":true,"follow_imports":"normal","follow_imports_for_stubs":false,"ignore_errors":false,"ignore_missing_imports":false,"implicit_optional":false,"implicit_reexport":false,"local_partial_types":false,"mypyc":false,"old_type_inference":false,"platform":"win32","plugins":[],"strict_concatenate":false,"strict_equality":true,"strict_optional":true,"warn_no_return":true,"warn_return_any":true,"warn_unreachable":true,"warn_unused_ignores":true},"path":"C:\\Users\\sgtsl\\PROJECTS\\ARC_Saga\\.venv\\Lib\\site-packages\\anyio\\_core\\_resources.py","plugin_data":null,"size":435,"suppressed":[],"version_id":"1.7.0"}